Metadata-Version: 2.4
Name: ttfemesh
Version: 0.1.3
Summary: A Python library for generating tensor train representations of finite element meshes
Home-page: https://github.com/MazenAli/TT-FEMesh
Author: Mazen Ali
Author-email: mazen.ali90@gmail.com
Project-URL: Source, https://github.com/MazenAli/TT-FEMesh
Project-URL: Documentation, https://tt-femesh.readthedocs.io/en/latest/
Keywords: tensor train finite elements meshing simulation
Classifier: Development Status :: 3 - Alpha
Classifier: Intended Audience :: Developers
Classifier: Intended Audience :: Science/Research
Classifier: License :: OSI Approved :: MIT License
Classifier: Programming Language :: Python :: 3.10
Classifier: Programming Language :: Python :: 3.11
Classifier: Programming Language :: Python :: 3.12
Classifier: Topic :: Scientific/Engineering :: Mathematics
Classifier: Topic :: Software Development :: Libraries
Classifier: Operating System :: POSIX :: Linux
Requires-Python: >=3.10,<3.13
License-File: LICENSE
Requires-Dist: numpy~=1.26
Requires-Dist: matplotlib~=3.9
Requires-Dist: torch~=2.5
Requires-Dist: torchTT~=0.3
Requires-Dist: teneva~=0.7
Dynamic: author
Dynamic: author-email
Dynamic: classifier
Dynamic: description
Dynamic: description-content-type
Dynamic: home-page
Dynamic: keywords
Dynamic: license-file
Dynamic: project-url
Dynamic: requires-dist
Dynamic: requires-python
Dynamic: summary
